mia_api/__init__.py
mia_api/config_file.py
mia_api/connect.py
mia_api/juice.py
mia_api/models.py
mia_api/utils.py
mia_api-0.0.4.dist-info/METADATA
mia_api-0.0.4.dist-info/WHEEL
mia_api-0.0.4.dist-info/top_level.txt
mia_api-0.0.4.dist-info/RECORD
