Metadata-Version: 2.1
Name: mia-api
Version: 0.0.4
Summary: A package to communicate with MIA API
Home-page: https://github.com/meteoia-team/mia_api
Author: MeteoIA
Author-email: meteoia.consult@meteoia.com
Project-URL: Bug Tracker, https://github.com/meteoia-team/mia_api/issues
Classifier: Programming Language :: Python :: 3
Requires-Python: >=3.6
Requires-Dist: fastapi
Requires-Dist: xarray
Requires-Dist: netCDF4
Requires-Dist: pandas
Requires-Dist: tqdm
Requires-Dist: tabulate
Requires-Dist: requests
